rich_color_support/__init__.py
rich_color_support-0.1.0.dist-info/LICENSE
rich_color_support-0.1.0.dist-info/METADATA
rich_color_support-0.1.0.dist-info/WHEEL
rich_color_support-0.1.0.dist-info/RECORD
