Metadata-Version: 2.3
Name: rich-color-support
Version: 0.1.0
Summary: Rich supports colors.
License: MIT
Author: Allen Chou
Author-email: f1470891079@gmail.com
Requires-Python: >=3.11,<4
Classifier: License :: OSI Approved :: MIT License
Classifier: Programming Language :: Python :: 3
Classifier: Programming Language :: Python :: 3.11
Classifier: Programming Language :: Python :: 3.12
Classifier: Programming Language :: Python :: 3.13
Requires-Dist: rich (>=13.0.0,<15.0.0)
Project-URL: Bug Tracker, https://github.com/allen2c/rich-color-support/issues
Project-URL: Documentation, https://allen2c.github.io/rich-color-support
Project-URL: Homepage, https://github.com/allen2c/rich-color-support
Project-URL: Repository, https://github.com/allen2c/rich-color-support
